{
  "Sach": {
    "MaSach": "1517177",
    "TuaDe": "Thám Tử Lừng Danh Conan (Tập 93)",
    "HinhAnh": "images/SACH_172.jpg",
    "TacGia": "Gosho Aoyama",
    "TheLoai": "Nhà Sách Tiki/Sách tiếng Việt/Truyện Tranh, Manga, Comic",
    "Gia": "18000",
    "GioiThieu": "<p>\n    <strong>\n        Thám Tử Lừng Danh Conan (Tập 93)\n    </strong>\n</p>\n<p>\n    Thi thể đã biến đi đâu!? “Vụ án xác chết biến mất trong bể bơi” sẽ được làm sáng tỏ! Bên cạnh đó, bóng dáng “Rum”, nhân\n    vật quyền lực thứ 2 của tổ chức Áo Đen sẽ theo sát Conan và Haibara!? Cũng trong tập này, “vụ án người cô thân thiết”, vụ\n    án mạng quái vật “Kamaitachi” với sự tham gia của Heiji... và sự mở đầu của “án mạng Kawanakajima” nơi máu của các cảnh sát\n    hình sự sẽ đổ xuống chiến trường xưa ở tỉnh Nagano... hứa hẹn sẽ mang tới nhiều điều bất ngờ!\n</p>\n<p>\n     \n</p>"
  }
}